splifft/__init__.py
splifft/__main__.py
splifft/config.py
splifft/core.py
splifft/inference.py
splifft/io.py
splifft/py.typed
splifft/training.py
splifft/models/__init__.py
splifft/models/bs_roformer.py
splifft/models/utils/__init__.py
splifft/models/utils/attend.py
splifft/models/utils/attend_sage.py
splifft/utils/mil.py
splifft-0.0.3.dist-info/METADATA
splifft-0.0.3.dist-info/WHEEL
splifft-0.0.3.dist-info/entry_points.txt
splifft-0.0.3.dist-info/licenses/LICENSE
splifft-0.0.3.dist-info/RECORD
