Metadata-Version: 2.4
Name: splifft
Version: 0.0.3
Summary: Lightweight utilities for music source separation.
Project-URL: Documentation, https://undef13.github.io/splifft/
Project-URL: Repository, https://github.com/undef13/splifft
Project-URL: Releases, https://github.com/undef13/splifft/releases
Author: undef13
License: MIT License
License-File: LICENSE
Keywords: artificial intelligence,audio,deep learning,music,source separation
Classifier: Development Status :: 3 - Alpha
Classifier: Environment :: Console
Classifier: Intended Audience :: Developers
Classifier: Intended Audience :: Science/Research
Classifier: License :: OSI Approved :: MIT License
Classifier: Operating System :: OS Independent
Classifier: Programming Language :: Python :: 3
Classifier: Programming Language :: Python :: 3.10
Classifier: Programming Language :: Python :: 3.11
Classifier: Programming Language :: Python :: 3.12
Classifier: Programming Language :: Python :: 3.13
Classifier: Topic :: Multimedia :: Sound/Audio :: Analysis
Classifier: Topic :: Scientific/Engineering :: Artificial Intelligence
Requires-Python: >=3.10
Requires-Dist: annotated-types>=0.7.0
Requires-Dist: einops>=0.8.1
Requires-Dist: numpy>=2.2.6
Requires-Dist: torch>=2.7.1
Provides-Extra: analysis
Requires-Dist: matplotlib>=3.10.3; extra == 'analysis'
Requires-Dist: polars>=1.30.0; extra == 'analysis'
Provides-Extra: cli
Requires-Dist: typer>=0.16.0; extra == 'cli'
Provides-Extra: config
Requires-Dist: pydantic>=2.11.5; extra == 'config'
Provides-Extra: inference
Requires-Dist: rich>=14.1.0; extra == 'inference'
Requires-Dist: soundfile>=0.13.1; (sys_platform == 'Windows') and extra == 'inference'
Requires-Dist: torchaudio>=2.7.1; extra == 'inference'
Requires-Dist: torchcodec>=0.6; extra == 'inference'
Provides-Extra: networking
Requires-Dist: aiolimiter>=1.2.1; extra == 'networking'
Requires-Dist: httpx[http2,socks,zstd]>=0.28.1; extra == 'networking'
Requires-Dist: orjson>=3.10.18; extra == 'networking'
Provides-Extra: sageattention
Requires-Dist: sageattention>=1.0.6; extra == 'sageattention'
